twevals/__init__.py
twevals/cli.py
twevals/config.py
twevals/context.py
twevals/decorators.py
twevals/discovery.py
twevals/formatters.py
twevals/parametrize.py
twevals/runner.py
twevals/schemas.py
twevals/storage.py
twevals/server/__init__.py
twevals/static/detail.css
twevals/static/detail.js
twevals/static/index.css
twevals/static/index.js
twevals/static/logo.png
twevals/static/tailwind-config.js
twevals/static/theme-init.js
twevals/templates/base.html
twevals/templates/detail.html
twevals/templates/index.html
twevals-0.0.0.dev20251206175718.dist-info/METADATA
twevals-0.0.0.dev20251206175718.dist-info/WHEEL
twevals-0.0.0.dev20251206175718.dist-info/entry_points.txt
twevals-0.0.0.dev20251206175718.dist-info/licenses/LICENSE
twevals-0.0.0.dev20251206175718.dist-info/RECORD
