Metadata-Version: 2.4
Name: twevals
Version: 0.0.0.dev20251206175718
Summary: A lightweight, code-first evaluation framework for testing AI agents and LLM applications
Project-URL: Homepage, https://github.com/camronh/Twevals
Project-URL: Repository, https://github.com/camronh/Twevals
Project-URL: Documentation, https://github.com/camronh/Twevals#readme
Author: Twevals Team
License: MIT
License-File: LICENSE
Keywords: agents,benchmark,cli,evaluation,llm,testing
Classifier: Development Status :: 3 - Alpha
Classifier: Environment :: Console
Classifier: Intended Audience :: Developers
Classifier: License :: OSI Approved :: MIT License
Classifier: Programming Language :: Python :: 3
Classifier: Programming Language :: Python :: 3 :: Only
Classifier: Programming Language :: Python :: 3.10
Classifier: Topic :: Software Development :: Testing
Requires-Python: >=3.10
Requires-Dist: click>=8.1.0
Requires-Dist: fastapi>=0.112.2
Requires-Dist: jinja2>=3.1.4
Requires-Dist: pydantic>=2.11.7
Requires-Dist: rich>=14.1.0
Requires-Dist: uvicorn>=0.30.1
Provides-Extra: dev
Requires-Dist: black>=25.1.0; extra == 'dev'
Requires-Dist: httpx>=0.27.0; extra == 'dev'
Requires-Dist: playwright>=1.48.0; extra == 'dev'
Requires-Dist: pytest-asyncio>=1.1.0; extra == 'dev'
Requires-Dist: pytest-cov>=6.2.1; extra == 'dev'
Requires-Dist: pytest-xdist>=3.8.0; extra == 'dev'
Requires-Dist: pytest>=8.4.1; extra == 'dev'
Requires-Dist: requests>=2.31.0; extra == 'dev'
Requires-Dist: ruff>=0.12.9; extra == 'dev'
